{"node_id": "concepts/kelly-bet-sizing-bug-fix-in-sequential-betting-simulations", "path": "concepts/kelly-bet-sizing-bug-fix-in-sequential-betting-simulations.md", "title": "Kelly Bet Sizing Bug Fix in Sequential Betting Simulations", "page_type": "concept", "tier": "hot", "quality_score": 0.0, "tags": ["betting", "kelly criterion", "simulation", "financial modeling"], "wikilinks": ["Kelly Criterion", "Copilot Session Checkpoint: Implementing Critical ML Fixes Sprint 28"], "last_verified": "2026-04-18", "summary": "The Kelly criterion is a formula used to determine the optimal size of a series of bets to maximize logarithmic growth of bankroll. Correct implementation in sequential simulations is critical to accurately model bankroll evolution and b...", "content_hash": "893c44ee5e8841800e5d81672c76d867925c020753757ccadd433283c5124153"}