{"node_id": "concepts/stale-model-detection-in-production-ml-systems", "path": "concepts/stale-model-detection-in-production-ml-systems.md", "title": "Stale Model Detection in Production ML Systems", "page_type": "concept", "tier": "hot", "quality_score": 0.0, "tags": ["model monitoring", "production ml", "model lifecycle", "reliability"], "wikilinks": ["Model Registry", "Copilot Session Checkpoint: Implementing Sprint 29 ML Improvements"], "last_verified": "2026-04-18", "summary": "Stale model detection identifies machine learning models that have become outdated due to age or data drift, signaling the need for retraining or replacement. It helps maintain model accuracy and reliability in production environments by...", "content_hash": "a0127452c69660bd2a45a2cea731e32508793b63064bb82d425894e5e4656e4a"}