{"node_id": "sources/copilot-session-checkpoint-sprint-35-props-page-audit", "path": "sources/copilot-session-checkpoint-sprint-35-props-page-audit.md", "title": "Copilot Session Checkpoint: Sprint 35 props page audit", "page_type": "source", "tier": "archive", "quality_score": 69.0, "tags": ["copilot-session", "checkpoint", "fileback", "durable-knowledge", "homelab", "nba-ml-engine", "agents", "dashboard"], "wikilinks": ["Homelab", "NBA ML Engine"], "last_verified": "2026-04-21", "summary": "The user is iterating on the NBA ML Engine project through sprint-based development on a homelab server (beelink-gti13). This session started with Sprint 34 (dashboard chart accuracy fixes), which was completed and deployed. Now Sprint 3...", "content_hash": "09c8c60a0848c01d187bb9fb89440a7f76914b7062fbd558cfd9a2da12f78aa7", "checkpoint_class": "project-progress", "retention_mode": "compress"}