{"node_id": "concepts/selective-tool-loading-and-context-hygiene", "path": "concepts/selective-tool-loading-and-context-hygiene.md", "title": "Selective Tool Loading and Context Hygiene", "page_type": "concept", "tier": "hot", "quality_score": 75.0, "tags": ["context-hygiene", "tool-loading", "ai-workflows", "token-economy"], "wikilinks": ["The Context Hygiene Principle", "The Token Economy Principle", "The Toolkit Principle"], "last_verified": "2026-04-08", "summary": "Selective tool loading is an operationalization of the Context Hygiene Principle, ensuring that only the tools, agents, and skills relevant to a specific task or project are loaded into an AI system's context. This minimizes context drif...", "content_hash": "114a8530972d43c291ebdd2ede365272854d471996eed8fe151cd164550d8883", "checkpoint_class": "", "retention_mode": ""}