{"node_id": "sources/copilot-session-checkpoint-sprint-10-retrain-in-progress", "path": "sources/copilot-session-checkpoint-sprint-10-retrain-in-progress.md", "title": "Copilot Session Checkpoint: Sprint 10 Retrain In Progress", "page_type": "source", "tier": "archive", "quality_score": 90.0, "tags": ["copilot-session", "checkpoint", "fileback", "durable-knowledge", "homelab", "nba-ml-engine", "dashboard", "nba", "machine-learning", "feature-engineering", "model-training", "hyperparameter-tuning"], "wikilinks": ["Quantile Crossing Fix in Gradient Boosting Models", "Warmstarting Hyperparameter Tuning with Optuna", "Target Encoding with Shifted Expanding Mean for Time-Series Features", "Per-Stat Model Selection and Ensemble Learning in NBA ML Engine", "NBA ML Engine", "Optuna", "LightGBM", "XGBoost"], "last_verified": "2026-04-21", "summary": "The user requested a comprehensive multi-step workflow for their NBA ML Engine project: merge the `feature/sprint-9-model-improvements` branch, review sprint 9's next steps (priorities 1-5), create and implement a full Sprint 10 plan, de...", "content_hash": "16dbfb50bfc498ca80a8128d4d738ee3e6a6bcb428f0ae2f22824403e4250157", "checkpoint_class": "project-progress", "retention_mode": "compress"}