{"node_id": "concepts/kernel-functions-in-svm", "path": "concepts/kernel-functions-in-svm.md", "title": "Kernel Functions in SVM", "page_type": "concept", "tier": "hot", "quality_score": 56.0, "tags": ["kernel-methods", "machine-learning", "non-linear-classification"], "wikilinks": ["Support Vector Machine Algorithm", "Support Vector Machine (SVM) Algorithm - GeeksforGeeks"], "last_verified": "2026-04-08", "summary": "Kernel functions are mathematical tools used in SVM to map data into higher-dimensional spaces, enabling the algorithm to handle non-linearly separable data. They allow SVM to find linear decision boundaries in transformed spaces without...", "content_hash": "296279d1d8674bbf77c85cd8300b7c5aec86d4dbde264954dda80548098d5cea", "checkpoint_class": "", "retention_mode": ""}