{"node_id": "concepts/homelab-media-domain-routing-lan-public-https-diagnostics", "path": "concepts/homelab-media-domain-routing-lan-public-https-diagnostics.md", "title": "Homelab Media Domain Routing: LAN and Public HTTPS Diagnostics", "page_type": "concept", "tier": "hot", "quality_score": 56.0, "tags": ["homelab", "routing", "dns", "cloudflare", "caddy", "media-services"], "wikilinks": ["Caddy handle_path Directive and Its Impact on Upstream URL Construction", "Copilot Session Checkpoint: Knightcrawler done, routing traced"], "last_verified": "2026-04-18", "summary": "A systematic approach to diagnosing and resolving media service routing issues in a homelab environment, focusing on the interplay between LAN DNS rewrites, Caddy proxy configuration, and Cloudflare tunnel/public DNS. The analysis distin...", "content_hash": "61fef158cdc29eb76a6d53a0d701c6a3158e0b74540014abe9e097bffb5eb74c", "checkpoint_class": "", "retention_mode": ""}