{"node_id": "concepts/dashboard-metrics-consistency-and-hit-rate-discrepancy-analysis", "path": "concepts/dashboard-metrics-consistency-and-hit-rate-discrepancy-analysis.md", "title": "Dashboard Metrics Consistency and Hit Rate Discrepancy Analysis", "page_type": "concept", "tier": "hot", "quality_score": 75.0, "tags": ["dashboard", "metrics", "hit-rate", "data-consistency"], "wikilinks": ["Registry Health Snapshot Tracking and Dashboard Integration", "PostgreSQL Materialized Views for Dashboard Optimization", "Copilot Session Checkpoint: Pipeline Resilience Fixes, Dashboard Metrics Investigation"], "last_verified": "2026-04-18", "summary": "Dashboard metrics consistency ensures that different views or endpoints reporting related statistics (such as hit rates) produce aligned and trustworthy results. Discrepancies can arise from differences in data sources, filtering criteri...", "content_hash": "68d0b7d5bcded2dce3cb7b81dbd7b215b3c0e4299ead35cf938f161002efef38", "checkpoint_class": "", "retention_mode": ""}