{"node_id": "concepts/persistence-of-residuals-in-model-save-load", "path": "concepts/persistence-of-residuals-in-model-save-load.md", "title": "Persistence of Residuals in Model Save/Load for Probability Prediction", "page_type": "concept", "tier": "hot", "quality_score": 53.0, "tags": ["model-serialization", "probabilistic-prediction", "residuals"], "wikilinks": ["Copilot Session Checkpoint: Sprint 12 Complete and Skills Installed"], "last_verified": "2026-04-18", "summary": "Persisting residual distributions in model serialization enables accurate probability predictions with uncertainty after model reload. Without saving residuals, prediction probability functions relying on residual distributions fail or d...", "content_hash": "7fccc9ec1bbc76421595519943e2c385f672193fef298a983b15918dddbf1b98", "checkpoint_class": "", "retention_mode": ""}