{"node_id": "sources/introducing-nested-learning-a-new-ml-paradigm-for-continual-learning", "path": "sources/introducing-nested-learning-a-new-ml-paradigm-for-continual-learning.md", "title": "Introducing Nested Learning: A New ML Paradigm for Continual Learning", "page_type": "source", "tier": "hot", "quality_score": 86.0, "tags": ["continual-learning", "machine-learning", "architecture", "optimization", "memory"], "wikilinks": ["Nested Learning Paradigm", "Continuum Memory System", "Hope Architecture", "Hope", "Titans", "Google Research"], "last_verified": "2026-04-21", "summary": "This article introduces Nested Learning, a novel machine learning paradigm that treats models as interconnected, nested optimization problems to address catastrophic forgetting in continual learning. The approach unifies architecture and...", "content_hash": "82508986191b67488efef12db4bcea979f80809f622b6b5037f075b0baabc995", "checkpoint_class": "", "retention_mode": ""}