{"node_id": "concepts/opencode-docker-container-bash-shell-configuration", "path": "concepts/opencode-docker-container-bash-shell-configuration.md", "title": "Opencode Docker Container Bash Shell Configuration", "page_type": "concept", "tier": "hot", "quality_score": 69.0, "tags": ["opencode", "docker", "bash", "container-configuration", "network-binding"], "wikilinks": ["Copilot Session Checkpoint: KnightCrawler Gating Fix, Opencode Bash Config"], "last_verified": "2026-04-18", "summary": "This concept describes the configuration of opencode and giniecode Docker containers to use the explicit bash shell path `/usr/bin/bash` by setting environment variables and updating Dockerfiles. It also covers the discovery that opencod...", "content_hash": "96bb13ec0b3de7ff804a35099d37418f4904a8d5954b3bca264a8e3442c367c0", "checkpoint_class": "", "retention_mode": ""}