{"node_id": "synthesis/structured-plan-artifacts-vs-context-management-complementary-strategies-for-err", "path": "synthesis/structured-plan-artifacts-vs-context-management-complementary-strategies-for-err.md", "title": "Structured Plan Artifacts vs. Context Management: Complementary Strategies for Error Reduction in Agentic Workflows", "page_type": "synthesis", "tier": "hot", "quality_score": 69.0, "tags": ["agentic workflows", "error reduction", "plan artifacts", "context management", "prompt engineering", "auditability"], "wikilinks": ["The Disposable Blueprint Principle", "The Context Hygiene Principle"], "last_verified": "2026-04-08", "summary": "How do structured plan artifacts and context management strategies complement or differ in reducing errors and improving agentic workflows?", "content_hash": "97adccb58170c0458271f25c758b8da2925defd557304e34f72d02b2d8bccf8c", "checkpoint_class": "", "retention_mode": ""}