{"node_id": "entities/qdrant", "path": "entities/qdrant.md", "title": "Qdrant", "page_type": "entity", "tier": "hot", "quality_score": 74.0, "tags": ["vector-db", "ai", "knowledge-management", "homelab"], "wikilinks": ["Homelab Service Inventory And Dashboard Synchronization", "MemPalace", "KnightCrawler", "Copilot Session Checkpoint: Homepage Overhaul And Resource Tuning", "Copilot Session Checkpoint: Training Status Tracker and OOM Fix"], "last_verified": "2026-04-22", "summary": "Qdrant is a vector database container running in the homelab, used for efficient storage and retrieval of vector embeddings. It supports MemPalace's persistent memory operations and is accessible via dashboard quick links for administrat...", "content_hash": "cb178e03e14a860951325977beaf76f2b92a21c08c95b6c18a0170cf5cdd1d23", "checkpoint_class": "", "retention_mode": ""}