{"node_id": "concepts/recurrent-neural-network-architecture", "path": "concepts/recurrent-neural-network-architecture.md", "title": "Recurrent Neural Network Architecture", "page_type": "concept", "tier": "hot", "quality_score": 82.0, "tags": ["rnn", "neural-network", "sequential-data", "machine-learning", "deep-learning"], "wikilinks": ["Artificial Neural Network Architecture", "Activation Functions in Neural Networks", "Backpropagation Learning Mechanism", "Introduction to Recurrent Neural Networks - GeeksforGeeks"], "last_verified": "2026-04-08", "summary": "Recurrent Neural Networks (RNNs) are a class of neural networks specialized for processing sequential data by maintaining a memory of previous inputs. Their architecture enables the modeling of temporal dependencies, making them suitable...", "content_hash": "d7ba0d8ccd6b03ca7da968ff657d556d2ebc38eeb78e3700cb8d5a7f1e7e2cfc", "checkpoint_class": "", "retention_mode": ""}